a2ln/__init__.py
a2ln/a2ln.py
a2ln-1.1.15.dist-info/licenses/COPYING
a2ln-1.1.15.dist-info/METADATA
a2ln-1.1.15.dist-info/WHEEL
a2ln-1.1.15.dist-info/entry_points.txt
a2ln-1.1.15.dist-info/top_level.txt
a2ln-1.1.15.dist-info/RECORD
