Metadata-Version: 2.4
Name: a2ln
Version: 1.1.15
Summary: A way to display Android phone notifications on Linux
Author-email: patri9ck <patri9ck@gmail.com>
License:                     GNU GENERAL PUBLIC LICENSE
Project-URL: Homepage, https://patri9ck.dev/a2ln/
Project-URL: Repository, https://github.com/patri9ck/a2ln-server
Project-URL: Issues, https://github.com/patri9ck/a2ln-server/issues
Classifier: License :: OSI Approved :: GNU General Public License v3 or later (GPLv3+)
Classifier: Programming Language :: Python
Classifier: Operating System :: POSIX :: Linux
Classifier: Topic :: Desktop Environment
Classifier: Topic :: Utilities
Requires-Python: >=3.8
License-File: COPYING
Requires-Dist: Pillow>=9.0.1
Requires-Dist: pygobject>=3.42.1
Requires-Dist: pyzmq>=24.0.0
Requires-Dist: qrcode>=7.3.1
Dynamic: license-file
